{
    "total_evaluated": 16,
    "total_safe": 16,
    "top_100": [
        {
            "entity_id": "globiint_zea_mays_feltia_repleta",
            "name": "Zea mays \u2192 Feltia repleta (hostOf)",
            "domain": "biology",
            "viability_score": 0.4315,
            "domain_scores": {
                "heat_score": 0.6877,
                "darcy_score": 0.0,
                "stress_score": 1.0,
                "arrhenius_score": 1.0,
                "biology_score": 0.1925,
                "logistic_score": 0.0365
            }
        },
        {
            "entity_id": "pdb_1e4l",
            "name": "PDB 1E4L: Crystal structure of the inactive mutant Monocot (Maize ZMGlu1) beta-glucosidase",
            "domain": "biology",
            "viability_score": 0.4288,
            "domain_scores": {
                "heat_score": 0.6877,
                "darcy_score": 0.0,
                "stress_score": 1.0,
                "arrhenius_score": 1.0,
                "biology_score": 0.1888,
                "logistic_score": 0.0237
            }
        },
        {
            "entity_id": "globiint_zea_mays_ctenicera_aeripennis_destructo",
            "name": "Zea mays \u2192 Ctenicera aeripennis destructor (eatenBy)",
            "domain": "biology",
            "viability_score": 0.3961,
            "domain_scores": {
                "heat_score": 0.6877,
                "darcy_score": 0.0,
                "stress_score": 1.0,
                "arrhenius_score": 1.0,
                "biology_score": 0.0274,
                "logistic_score": 0.0206
            }
        },
        {
            "entity_id": "ncbi_gene_822061",
            "name": "ABI3",
            "domain": "biology",
            "viability_score": 0.3892,
            "domain_scores": {
                "heat_score": 0.6877,
                "darcy_score": 0.0,
                "stress_score": 1.0,
                "arrhenius_score": 1.0,
                "biology_score": 0.0061,
                "logistic_score": 0.0031
            }
        },
        {
            "entity_id": "globiint_zea_mays_olene_inclusa",
            "name": "Zea mays \u2192 Olene inclusa (hostOf)",
            "domain": "biology",
            "viability_score": 0.3892,
            "domain_scores": {
                "heat_score": 0.6877,
                "darcy_score": 0.0,
                "stress_score": 1.0,
                "arrhenius_score": 1.0,
                "biology_score": 0.0061,
                "logistic_score": 0.0031
            }
        },
        {
            "entity_id": "globiint_zea_mays_orgyia_osseata",
            "name": "Zea mays \u2192 Orgyia osseata (hostOf)",
            "domain": "biology",
            "viability_score": 0.3892,
            "domain_scores": {
                "heat_score": 0.6877,
                "darcy_score": 0.0,
                "stress_score": 1.0,
                "arrhenius_score": 1.0,
                "biology_score": 0.0061,
                "logistic_score": 0.0031
            }
        },
        {
            "entity_id": "globiint_zea_mays_bombus_pratorum",
            "name": "Zea mays \u2192 Bombus pratorum (flowersVisitedBy)",
            "domain": "biology",
            "viability_score": 0.3892,
            "domain_scores": {
                "heat_score": 0.6877,
                "darcy_score": 0.0,
                "stress_score": 1.0,
                "arrhenius_score": 1.0,
                "biology_score": 0.0061,
                "logistic_score": 0.0031
            }
        },
        {
            "entity_id": "globiint_zea_mays_cerotoma_trifurcata",
            "name": "Zea mays \u2192 Cerotoma trifurcata (eatenBy)",
            "domain": "biology",
            "viability_score": 0.3892,
            "domain_scores": {
                "heat_score": 0.6877,
                "darcy_score": 0.0,
                "stress_score": 1.0,
                "arrhenius_score": 1.0,
                "biology_score": 0.0061,
                "logistic_score": 0.0031
            }
        },
        {
            "entity_id": "globiint_zea_mays_carpophilus_lugubris",
            "name": "Zea mays \u2192 Carpophilus lugubris (interactsWith)",
            "domain": "biology",
            "viability_score": 0.3892,
            "domain_scores": {
                "heat_score": 0.6877,
                "darcy_score": 0.0,
                "stress_score": 1.0,
                "arrhenius_score": 1.0,
                "biology_score": 0.0061,
                "logistic_score": 0.0031
            }
        },
        {
            "entity_id": "globiint_zea_mays_carpophilus",
            "name": "Zea mays \u2192 Carpophilus (eatenBy)",
            "domain": "biology",
            "viability_score": 0.3892,
            "domain_scores": {
                "heat_score": 0.6877,
                "darcy_score": 0.0,
                "stress_score": 1.0,
                "arrhenius_score": 1.0,
                "biology_score": 0.0061,
                "logistic_score": 0.0031
            }
        },
        {
            "entity_id": "globiint_zea_mays_cadra_cautella",
            "name": "Zea mays \u2192 Cadra cautella (eatenBy)",
            "domain": "biology",
            "viability_score": 0.3892,
            "domain_scores": {
                "heat_score": 0.6877,
                "darcy_score": 0.0,
                "stress_score": 1.0,
                "arrhenius_score": 1.0,
                "biology_score": 0.0061,
                "logistic_score": 0.0031
            }
        },
        {
            "entity_id": "globiint_zea_mays_brithys_pancratii",
            "name": "Zea mays \u2192 Brithys pancratii (hostOf)",
            "domain": "biology",
            "viability_score": 0.3892,
            "domain_scores": {
                "heat_score": 0.6877,
                "darcy_score": 0.0,
                "stress_score": 1.0,
                "arrhenius_score": 1.0,
                "biology_score": 0.0061,
                "logistic_score": 0.0031
            }
        },
        {
            "entity_id": "globiint_zea_mays_brachypera_zoilus",
            "name": "Zea mays \u2192 Brachypera zoilus (eatenBy)",
            "domain": "biology",
            "viability_score": 0.3892,
            "domain_scores": {
                "heat_score": 0.6877,
                "darcy_score": 0.0,
                "stress_score": 1.0,
                "arrhenius_score": 1.0,
                "biology_score": 0.0061,
                "logistic_score": 0.0031
            }
        },
        {
            "entity_id": "globiint_zea_mays_borbo_gemella",
            "name": "Zea mays \u2192 Borbo gemella (hostOf)",
            "domain": "biology",
            "viability_score": 0.3892,
            "domain_scores": {
                "heat_score": 0.6877,
                "darcy_score": 0.0,
                "stress_score": 1.0,
                "arrhenius_score": 1.0,
                "biology_score": 0.0061,
                "logistic_score": 0.0031
            }
        },
        {
            "entity_id": "globiint_zea_mays_bombus_terrestris",
            "name": "Zea mays \u2192 Bombus terrestris (flowersVisitedBy)",
            "domain": "biology",
            "viability_score": 0.3892,
            "domain_scores": {
                "heat_score": 0.6877,
                "darcy_score": 0.0,
                "stress_score": 1.0,
                "arrhenius_score": 1.0,
                "biology_score": 0.0061,
                "logistic_score": 0.0031
            }
        },
        {
            "entity_id": "agristack_uttar_pradesh_maize_2023",
            "name": "Maize \u2014 Uttar Pradesh",
            "domain": "environment",
            "viability_score": 0.3892,
            "domain_scores": {
                "heat_score": 0.6877,
                "darcy_score": 0.0,
                "stress_score": 1.0,
                "arrhenius_score": 1.0,
                "biology_score": 0.0061,
                "logistic_score": 0.0031
            }
        }
    ]
}